<?xml version = '1.0' encoding = 'UTF-8'?>
<Relation class="oracle.dbtools.crest.model.design.logical.Relation" name="Relation_6" directorySegmentName="seg_0" id="7C39BBB7-494E-BDEE-E02D-B965178E71C5">
<createdBy>nico-</createdBy>
<createdTime>2019-04-02 17:38:49 UTC</createdTime>
<ownerDesignName>trabajo internet</ownerDesignName>
<engineerTo>
<item key="BCFDEDFF-15E7-D684-81ED-8DF7C02774D3" value="true"/>
</engineerTo>
<identifying>false</identifying>
<optionalSource>false</optionalSource>
<optionalTarget>false</optionalTarget>
<sourceCardinality>1</sourceCardinality>
<sourceEntity>613DD738-7CF5-4561-9AF2-4EAF8E001216</sourceEntity>
<targetCardinalityString>*</targetCardinalityString>
<targetEntity>6121F199-D5D9-9332-E0D9-02AD3FF090CE</targetEntity>
<transferable>true</transferable>
<deleteRule>NO ACTION</deleteRule>
</Relation>